infeze/__init__.py
infeze/_version.py
infeze/py.typed
infeze/backports/langchain/tongyi.py
infeze-0.0.2.dist-info/METADATA
infeze-0.0.2.dist-info/WHEEL
infeze-0.0.2.dist-info/top_level.txt
infeze-0.0.2.dist-info/RECORD
