Metadata-Version: 2.1
Name: infeze
Version: 0.0.2
Author-email: huaxlin <huaxlin33@gmail.com>
Project-URL: Home, https://github.com/huaxlin/infeze
Requires-Python: >=3.8
Provides-Extra: dev
Requires-Dist: bump2version ; extra == 'dev'
Requires-Dist: mypy ; extra == 'dev'
